py_diceware/__init__.py
py_diceware/__main__.py
py_diceware/cli.py
py_diceware/config.py
py_diceware/passphrase.py
py_diceware/roll_dice.py
py_diceware/wordlist.py
py_diceware/wordlists/diceware.wordlist.asc
py_diceware-0.1.0.dist-info/LICENSE
py_diceware-0.1.0.dist-info/METADATA
py_diceware-0.1.0.dist-info/WHEEL
py_diceware-0.1.0.dist-info/entry_points.txt
py_diceware-0.1.0.dist-info/top_level.txt
py_diceware-0.1.0.dist-info/RECORD
